<?xml version="1.0" encoding="UTF-8"?>
<GeocodeResponse>
 <status>OK</status>
 <result>
  <type>locality</type>
  <type>political</type>
  <formatted_address>9556 Liebenfels, Austria</formatted_address>
  <address_component>
   <long_name>Liebenfels</long_name>
   <short_name>Liebenfels</short_name>
   <type>locality</type>
   <type>political</type>
  </address_component>
  <address_component>
   <long_name>Gemeinde Liebenfels</long_name>
   <short_name>Gemeinde Liebenfels</short_name>
   <type>administrative_area_level_3</type>
   <type>political</type>
  </address_component>
  <address_component>
   <long_name>Sankt Veit an der Glan District</long_name>
   <short_name>Sankt Veit an der Glan District</short_name>
   <type>administrative_area_level_2</type>
   <type>political</type>
  </address_component>
  <address_component>
   <long_name>Carinthia</long_name>
   <short_name>Carinthia</short_name>
   <type>administrative_area_level_1</type>
   <type>political</type>
  </address_component>
  <address_component>
   <long_name>Austria</long_name>
   <short_name>AT</short_name>
   <type>country</type>
   <type>political</type>
  </address_component>
  <address_component>
   <long_name>9556</long_name>
   <short_name>9556</short_name>
   <type>postal_code</type>
  </address_component>
  <geometry>
   <location>
    <lat>46.7372269</lat>
    <lng>14.2878116</lng>
   </location>
   <location_type>APPROXIMATE</location_type>
   <viewport>
    <southwest>
     <lat>46.7295793</lat>
     <lng>14.2718042</lng>
    </southwest>
    <northeast>
     <lat>46.7448734</lat>
     <lng>14.3038190</lng>
    </northeast>
   </viewport>
  </geometry>
  <place_id>ChIJ6Xflu3BucEcRwkaq8twU8eI</place_id>
 </result>
</GeocodeResponse>
