<?xml version="1.0" encoding="UTF-8"?>
<GeocodeResponse>
 <status>OK</status>
 <result>
  <type>administrative_area_level_3</type>
  <type>political</type>
  <formatted_address>Sulmeck-Greith, Austria</formatted_address>
  <address_component>
   <long_name>Sulmeck-Greith</long_name>
   <short_name>Sulmeck-Greith</short_name>
   <type>administrative_area_level_3</type>
   <type>political</type>
  </address_component>
  <address_component>
   <long_name>Deutschlandsberg</long_name>
   <short_name>Deutschlandsberg</short_name>
   <type>administrative_area_level_2</type>
   <type>political</type>
  </address_component>
  <address_component>
   <long_name>Steiermark</long_name>
   <short_name>Steiermark</short_name>
   <type>administrative_area_level_1</type>
   <type>political</type>
  </address_component>
  <address_component>
   <long_name>Austria</long_name>
   <short_name>AT</short_name>
   <type>country</type>
   <type>political</type>
  </address_component>
  <geometry>
   <location>
    <lat>46.7535208</lat>
    <lng>15.3323817</lng>
   </location>
   <location_type>APPROXIMATE</location_type>
   <viewport>
    <southwest>
     <lat>46.6981500</lat>
     <lng>15.2853600</lng>
    </southwest>
    <northeast>
     <lat>46.7732599</lat>
     <lng>15.3588099</lng>
    </northeast>
   </viewport>
   <bounds>
    <southwest>
     <lat>46.6981500</lat>
     <lng>15.2853600</lng>
    </southwest>
    <northeast>
     <lat>46.7732599</lat>
     <lng>15.3588099</lng>
    </northeast>
   </bounds>
  </geometry>
  <place_id>ChIJtV75gsy_b0cRwqJZ-ZRI3h4</place_id>
 </result>
</GeocodeResponse>
