<?xml version="1.0" encoding="UTF-8"?>
<GeocodeResponse>
 <status>OK</status>
 <result>
  <type>country</type>
  <type>political</type>
  <formatted_address>Guam</formatted_address>
  <address_component>
   <long_name>Guam</long_name>
   <short_name>GU</short_name>
   <type>country</type>
   <type>political</type>
  </address_component>
  <geometry>
   <location>
    <lat>13.4443040</lat>
    <lng>144.7937310</lng>
   </location>
   <location_type>APPROXIMATE</location_type>
   <viewport>
    <southwest>
     <lat>13.2340731</lat>
     <lng>144.6183881</lng>
    </southwest>
    <northeast>
     <lat>13.6543391</lat>
     <lng>144.9566722</lng>
    </northeast>
   </viewport>
   <bounds>
    <southwest>
     <lat>13.1022175</lat>
     <lng>144.4647218</lng>
    </southwest>
    <northeast>
     <lat>13.7994072</lat>
     <lng>145.1129150</lng>
    </northeast>
   </bounds>
  </geometry>
  <place_id>ChIJ7yQPk_92H2cRpuWzxZGucVU</place_id>
 </result>
</GeocodeResponse>
