<?xml version="1.0" encoding="UTF-8"?>
<GeocodeResponse>
 <status>OK</status>
 <result>
  <type>country</type>
  <type>political</type>
  <formatted_address>Maldives</formatted_address>
  <address_component>
   <long_name>Maldives</long_name>
   <short_name>MV</short_name>
   <type>country</type>
   <type>political</type>
  </address_component>
  <geometry>
   <location>
    <lat>1.9772276</lat>
    <lng>73.5361010</lng>
   </location>
   <location_type>APPROXIMATE</location_type>
   <viewport>
    <southwest>
     <lat>1.8212832</lat>
     <lng>73.4862398</lng>
    </southwest>
    <northeast>
     <lat>2.1331721</lat>
     <lng>73.5859623</lng>
    </northeast>
   </viewport>
   <bounds>
    <southwest>
     <lat>-1.2907844</lat>
     <lng>71.7517090</lng>
    </southwest>
    <northeast>
     <lat>7.5149809</lat>
     <lng>74.7290038</lng>
    </northeast>
   </bounds>
  </geometry>
  <place_id>ChIJvXv7qr-ZtSQRiWKVgeEJRUE</place_id>
 </result>
</GeocodeResponse>
