<?xml version="1.0" encoding="UTF-8"?>
<GeocodeResponse>
 <status>OK</status>
 <result>
  <type>administrative_area_level_3</type>
  <type>political</type>
  <formatted_address>Regensburg, Germany</formatted_address>
  <address_component>
   <long_name>Regensburg</long_name>
   <short_name>R</short_name>
   <type>administrative_area_level_3</type>
   <type>political</type>
  </address_component>
  <address_component>
   <long_name>Upper Palatinate</long_name>
   <short_name>Upper Palatinate</short_name>
   <type>administrative_area_level_2</type>
   <type>political</type>
  </address_component>
  <address_component>
   <long_name>Bavaria</long_name>
   <short_name>BY</short_name>
   <type>administrative_area_level_1</type>
   <type>political</type>
  </address_component>
  <address_component>
   <long_name>Germany</long_name>
   <short_name>DE</short_name>
   <type>country</type>
   <type>political</type>
  </address_component>
  <geometry>
   <location>
    <lat>49.0134074</lat>
    <lng>12.1016310</lng>
   </location>
   <location_type>APPROXIMATE</location_type>
   <viewport>
    <southwest>
     <lat>48.7649053</lat>
     <lng>11.6591858</lng>
    </southwest>
    <northeast>
     <lat>49.2232842</lat>
     <lng>12.4909978</lng>
    </northeast>
   </viewport>
   <bounds>
    <southwest>
     <lat>48.7649053</lat>
     <lng>11.6591858</lng>
    </southwest>
    <northeast>
     <lat>49.2232842</lat>
     <lng>12.4909978</lng>
    </northeast>
   </bounds>
  </geometry>
  <place_id>ChIJIWdnpCHBn0cRPLc80Q0Fk6E</place_id>
 </result>
</GeocodeResponse>
