<?xml version="1.0" encoding="UTF-8"?>
<GeocodeResponse>
 <status>OK</status>
 <result>
  <type>administrative_area_level_2</type>
  <type>political</type>
  <formatted_address>Eure-et-Loir, France</formatted_address>
  <address_component>
   <long_name>Eure-et-Loir</long_name>
   <short_name>Eure-et-Loir</short_name>
   <type>administrative_area_level_2</type>
   <type>political</type>
  </address_component>
  <address_component>
   <long_name>Centre-Val de Loire</long_name>
   <short_name>Centre-Val de Loire</short_name>
   <type>administrative_area_level_1</type>
   <type>political</type>
  </address_component>
  <address_component>
   <long_name>France</long_name>
   <short_name>FR</short_name>
   <type>country</type>
   <type>political</type>
  </address_component>
  <geometry>
   <location>
    <lat>48.5525242</lat>
    <lng>1.1989814</lng>
   </location>
   <location_type>APPROXIMATE</location_type>
   <viewport>
    <southwest>
     <lat>47.9538179</lat>
     <lng>0.7556760</lng>
    </southwest>
    <northeast>
     <lat>48.9410290</lat>
     <lng>1.9945600</lng>
    </northeast>
   </viewport>
   <bounds>
    <southwest>
     <lat>47.9538179</lat>
     <lng>0.7556760</lng>
    </southwest>
    <northeast>
     <lat>48.9410290</lat>
     <lng>1.9945600</lng>
    </northeast>
   </bounds>
  </geometry>
  <place_id>ChIJozitvHMK5EcRICczBdfIDQM</place_id>
 </result>
</GeocodeResponse>
