<?xml version="1.0" encoding="UTF-8"?>
<GeocodeResponse>
 <status>OK</status>
 <result>
  <type>postal_town</type>
  <formatted_address>Dunblane FK15, UK</formatted_address>
  <address_component>
   <long_name>Dunblane</long_name>
   <short_name>Dunblane</short_name>
   <type>postal_town</type>
  </address_component>
  <address_component>
   <long_name>United Kingdom</long_name>
   <short_name>GB</short_name>
   <type>country</type>
   <type>political</type>
  </address_component>
  <address_component>
   <long_name>FK15</long_name>
   <short_name>FK15</short_name>
   <type>postal_code</type>
   <type>postal_code_prefix</type>
  </address_component>
  <geometry>
   <location>
    <lat>56.2522109</lat>
    <lng>-3.9554785</lng>
   </location>
   <location_type>APPROXIMATE</location_type>
   <viewport>
    <southwest>
     <lat>56.1589340</lat>
     <lng>-4.0490086</lng>
    </southwest>
    <northeast>
     <lat>56.3089104</lat>
     <lng>-3.8116802</lng>
    </northeast>
   </viewport>
   <bounds>
    <southwest>
     <lat>56.1589340</lat>
     <lng>-4.0490086</lng>
    </southwest>
    <northeast>
     <lat>56.3089104</lat>
     <lng>-3.8116802</lng>
    </northeast>
   </bounds>
  </geometry>
  <partial_match>true</partial_match>
  <place_id>ChIJlYyDeFSPiEgRXDyIqs1Ni_Q</place_id>
 </result>
</GeocodeResponse>
